<?xml version="1.0" encoding="UTF-8" standalone="yes"?>
<node artifactManager="be.nabu.eai.module.services.crud.CRUDArtifactManager" created="2021-03-05T13:20:26.156+01:00" lastModified="2025-08-26T12:22:01.324+02:00" leaf="false" version="18">
    <environmentId>ares</environmentId>
    <hidden>false</hidden>
    <locked>false</locked>
    <properties/>
    <references>nabu.frameworks.signals.database.types.signalRule</references>
    <references>nabu.services.crud.provider.basic.provider</references>
</node>
