<?xml version="1.0" encoding="UTF-8" standalone="yes"?>
<node artifactManager="be.nabu.eai.module.services.crud.CRUDArtifactManager" created="2023-05-16T12:01:32.581+02:00" lastModified="2025-08-26T12:22:01.336+02:00" leaf="false" version="6">
    <environmentId>ares</environmentId>
    <hidden>false</hidden>
    <locked>false</locked>
    <properties/>
    <references>nabu.frameworks.signals.database.types.signalWindow</references>
    <references>nabu.services.crud.provider.basic.provider</references>
</node>
